fibcrypt/__init__.py
fibcrypt/crypto_utils.py
fibcrypt/fib.py
fibcrypt/kdf.py
fibcrypt/utils.py
fibcrypt-0.1.5.dist-info/METADATA
fibcrypt-0.1.5.dist-info/WHEEL
fibcrypt-0.1.5.dist-info/top_level.txt
fibcrypt-0.1.5.dist-info/RECORD
