Metadata-Version: 2.4
Name: fibcrypt
Version: 0.1.5
Summary: A fast Fibonacci-based cryptographic toolkit
Author: Hakan Damar
Author-email: hakan.damar@linux.com
Classifier: Programming Language :: Python :: 3
Classifier: Operating System :: OS Independent
Classifier: License :: OSI Approved :: MIT License
Classifier: Topic :: Security :: Cryptography
Requires-Python: >=3.8
Requires-Dist: pycryptodomex>=3.22.0
Dynamic: author
Dynamic: author-email
Dynamic: classifier
Dynamic: description
Dynamic: description-content-type
Dynamic: requires-dist
Dynamic: requires-python
Dynamic: summary
